<?xml version="1.0" encoding="utf-8" ?>
<dwsync>
<file name="favicon.png" server="vyperlink.com//kit95/" local="132503933348654927" remote="132507280800000000" Dst="2" />
<file name="apple-touch-icon.png" server="vyperlink.com//kit95/" local="132504479053008042" remote="132507280800000000" Dst="2" />
<file name="LogoLucco2._black_textpng.png" server="vyperlink.com//kit95/" local="132504043300000000" remote="132507282600000000" Dst="2" />
<file name="apple-touch-icon.png" server="vyperlink.com//casagalpon/" local="132504479053008042" remote="132555794400000000" Dst="2" />
<file name="favicon.png" server="vyperlink.com//casagalpon/" local="132503933348654927" remote="132555794400000000" Dst="2" />
<file name="LogoLucco2._black_textpng.png" server="vyperlink.com//casagalpon/" local="132504043300000000" remote="132555794400000000" Dst="2" />
<file name="LogoLuccogreen.svg" server="vyperlink.com//casagalpon/" local="132558235360000000" remote="132560221800000000" Dst="2" />
<file name="vyperlink_logo_outline.svg" server="vyperlink.com//casagalpon/" local="132560224200000000" remote="132560248200000000" Dst="2" />
<file name="apple-touch-icon.png" server="vyperlink.com//kit100/" local="132504479053008042" remote="132560590800000000" Dst="2" />
<file name="LogoLuccogreen.svg" server="vyperlink.com//kit100/" local="132560908743159247" remote="132560912400000000" Dst="2" />
<file name="LogoLucco2._black_textpng.png" server="vyperlink.com//kit100/" local="132504043300000000" remote="132560591400000000" Dst="2" />
<file name="favicon.png" server="vyperlink.com//kit100/" local="132503933348654927" remote="132560590800000000" Dst="2" />
<file name="vyperlink_logo_outline.svg" server="vyperlink.com//kit100/" local="132560224200000000" remote="132560913000000000" Dst="2" />
<file name="favicon.png" server="vyperlink.com//kit20/" local="132503933348654927" remote="132567801000000000" Dst="2" />
<file name="apple-touch-icon.png" server="vyperlink.com//kit20/" local="132504479053008042" remote="132567801000000000" Dst="2" />
<file name="LogoLuccogreen.svg" server="vyperlink.com//kit20/" local="132560908743159247" remote="132567802800000000" Dst="2" />
<file name="LogoLucco2._black_textpng.png" server="vyperlink.com//kit20/" local="132504043300000000" remote="132567802800000000" Dst="2" />
<file name="vyperlink_logo_outline.svg" server="vyperlink.com//kit20/" local="132560224200000000" remote="132567802800000000" Dst="2" />
<file name="vyperlink_logo_outline.png" server="vyperlink.com//kit20/" local="132560850660000000" remote="132567802800000000" Dst="2" />
<file name="Kit20_AR_QR.svg" server="vyperlink.com//kit20/" local="132569485734767699" remote="132569510400000000" Dst="2" />
</dwsync>